oracollector/__init__.py
oracollector/__main__.py
oracollector/config_oracle.yaml
pgcollector/.DS_Store
pgcollector/__init__.py
pgcollector/__main__.py
pgcollector/config.yaml
pgcollector/dbobjectnames.sql
pgcollector/extracts/pg-extract-35.204.159.2.zip
compare/__init__.py
compare/__main__.py
importer/__init__.py
importer/__main__.py
importer/create_pg_user.sql
importer/extracts/.gitignore
reporter/.DS_Store
reporter/.gitignore
reporter/__init__.py
reporter/__main__.py
reporter/queries/column_type_mismatch.sql
reporter/queries/instances.sql
reporter/queries/line_count_mismatch.sql
reporter/queries/line_count_mismatch_detailed.sql
reporter/queries/missing_columns.sql
reporter/queries/missing_indexes.sql
reporter/queries/missing_objects.sql
reporter/queries/missing_plsql.sql
reporter/queries/missing_role_grants.sql
reporter/queries/missing_sys_privs.sql
reporter/queries/object_counts.sql
reporter/queries/object_counts_mismatch.sql
reporter/queries/object_counts_per_schema.sql
reporter/queries/object_counts_per_schema_mismatch.sql
reporter/query_config.yaml
reporter/report.css
oracle2postgres_schema_validator-0.1.10.dist-info/LICENSE
oracle2postgres_schema_validator-0.1.10.dist-info/METADATA
oracle2postgres_schema_validator-0.1.10.dist-info/WHEEL
oracle2postgres_schema_validator-0.1.10.dist-info/entry_points.txt
oracle2postgres_schema_validator-0.1.10.dist-info/RECORD
